rtl/FSM_trafficLight/modified_code.v
//here 3 extra FF for light which was unecesariy will not be generated!! 
module cyclic_lamp(clk,light);
input clk;
output reg[0:2] light;
parameter s0=0,s1=1,s2=2;
parameter red=3'b100,green=3'b010,yellow=3'b001;
reg[0:1] state; 

always @(posedge clk)
case (state)

s0: state<=s1;
s1: state<=s2;
s2: state<=s0;
default: state<=s0;
endcase

always @(state)
case (state)
s0: light=red;
s1: light=green;
s2: light=yellow;
default: light=red;
endcase
endmodule

rtl/FSM_trafficLight/tb_lamp.v
module tb_lamp;
reg clk;
wire[0:2] light;
cyclic_lamp LAMP(clk,light);
always #5 clk=~clk;
initial begin
    clk=1'b0;#100 $finish;
end

initial 
begin
    $dumpfile("cyclic.vcd");
    $dumpvars(0,tb_lamp);
    $monitor($time,"RGY: %b",light);
end
endmodule

rtl/FSM_trafficLight/cyclic.vcd
$date
	Mon Apr 13 22:07:05 2026
$end
$version
	Icarus Verilog
$end
$timescale
	1s
$end
$scope module tb_lamp $end
$var wire 3 ! light [0:2] $end
$var reg 1 " clk $end
$scope module LAMP $end
$var wire 1 " clk $end
$var parameter 3 # green $end
$var parameter 3 $ red $end
$var parameter 32 % s0 $end
$var parameter 32 & s1 $end
$var parameter 32 ' s2 $end
$var parameter 3 ( yellow $end
$var reg 3 ) light [0:2] $end
$var reg 2 * state [0:1] $end
$upscope $end
$upscope $end
$enddefinitions $end
$comment Show the parameter values. $end
$dumpall
b1 (
b10 '
b1 &
b0 %
b100 $
b10 #
$end
#0
$dumpvars
bx *
bx )
0"
bx !
$end
#5
b0 *
b100 !
b100 )
1"
#10
0"
#15
b1 *
b10 !
b10 )
1"
#20
0"
#25
b10 *
b1 !
b1 )
1"
#30
0"
#35
b0 *
b100 !
b100 )
1"
#40
0"
#45
b1 *
b10 !
b10 )
1"
#50
0"
#55
b10 *
b1 !
b1 )
1"
#60
0"
#65
b0 *
b100 !
b100 )
1"
#70
0"
#75
b1 *
b10 !
b10 )
1"
#80
0"
#85
b10 *
b1 !
b1 )
1"
#90
0"
#95
b0 *
b100 !
b100 )
1"
