rtl/parity_detector/parityDetector_fsm.v
//parity deterctor(0->even no of 1s,1->odd no of 1s) using moore machine
module parityDetector(x,clk,z);
input x,clk;
output reg z;
reg even_odd;//machine_state//this code cause generation of latch for even_odd o/ p
parameter even=0,odd=1;

always @(posedge clk)

case(even_odd)

even: begin
    z<=x ? 1:0;//if x=1,than o/p=1
    even_odd<=x ? odd:even;//if x=1 than updated state even_odd=odd
end
odd:begin
    z<=x?0:1;//if x=1,than o/p=0
    even_odd<=x?even:odd;//if x=1 than updated state even_odd=even
end
default: even_odd<=even;

endcase
 
endmodule
//total 2 FF generated here,one for z and one for even_odd

rtl/parity_detector/testbench_parity.v
module tb_parity;
reg clk,x; wire z;

parityDetector PAR(x,clk,z);
initial
begin
    $dumpfile("parity.vcd");
    $dumpvars(0,tb_parity);
    clk=1'b0;
end
always #5 clk=~clk;
initial 
begin
    #2 x=0;  #10 x=1; #10 x=1; #10 x=1;
    #10 x=0; #10 x=1; #10 x=1;#10 x=0;
    #10 x=0; #10 x=1; #10 x=1;#10 x=0;
    #10 $finish;
end
endmodule

rtl/parity_detector/parity.vcd
$date
	Tue Apr 14 12:54:11 2026
$end
$version
	Icarus Verilog
$end
$timescale
	1s
$end
$scope module tb_parity $end
$var wire 1 ! z $end
$var reg 1 " clk $end
$var reg 1 # x $end
$scope module PAR $end
$var wire 1 " clk $end
$var wire 1 # x $end
$var parameter 32 $ even $end
$var parameter 32 % odd $end
$var reg 1 & even_odd $end
$var reg 1 ! z $end
$upscope $end
$upscope $end
$enddefinitions $end
$comment Show the parameter values. $end
$dumpall
b1 %
b0 $
$end
#0
$dumpvars
x&
x#
0"
x!
$end
#2
0#
#5
0&
1"
#10
0"
#12
1#
#15
1&
1!
1"
#20
0"
#25
0&
0!
1"
#30
0"
#35
1&
1!
1"
#40
0"
#42
0#
#45
1"
#50
0"
#52
1#
#55
0&
0!
1"
#60
0"
#65
1&
1!
1"
#70
0"
#72
0#
#75
1"
#80
0"
#85
1"
#90
0"
#92
1#
#95
0&
0!
1"
#100
0"
#105
1&
1!
1"
#110
0"
#112
0#
